app/__init__.py
app/api.py
app/config.py
app/models.py
app/api/__init__.py
app/api/chat.py
app/api/execution.py
app/api/graph_config.py
app/api/graphs.py
app/api/jobs.py
app/api/session.py
app/api/tracing.py
app/api/auth/__init__.py
app/api/auth/api_key_manager.py
app/api/auth/routes.py
app/components/__init__.py
app/components/billing_service.py
app/components/consul_discovery.py
app/components/mcp_service.py
app/components/model_service.py
app/components/multimodal_processor.py
app/components/session_service.py
app/components/storage_service.py
app/components/task_service.py
app/components/tracing_service.py
app/components/user_service.py
app/core/__init__.py
app/core/config/__init__.py
app/core/config/env_validator.py
app/core/errors/__init__.py
app/core/errors/error_handler.py
app/core/resilience/__init__.py
app/core/resilience/circuit_breaker.py
app/core/resilience/connection_limiter.py
app/core/resilience/rate_limiter.py
app/core/resilience/system_protection.py
app/core/resilience/timeouts.py
app/graphs/__init__.py
app/graphs/base_graph.py
app/graphs/coding_graph.py
app/graphs/conversation_graph.py
app/graphs/graph_config_service.py
app/graphs/graph_registry_with_auth.py
app/graphs/graph_stream.py
app/graphs/research_graph.py
app/graphs/smart_agent_graph.py
app/graphs/utils/__init__.py
app/graphs/utils/context_init.py
app/graphs/utils/context_schema.py
app/graphs/utils/context_update.py
app/graphs/utils/memory_curation_utils.py
app/graphs/utils/memory_utils.py
app/middleware/__init__.py
app/nodes/__init__.py
app/nodes/agent_executor_node.py
app/nodes/base_node.py
app/nodes/failsafe_node.py
app/nodes/guardrail_node.py
app/nodes/reason_node.py
app/nodes/response_node.py
app/nodes/tool_node.py
app/types/__init__.py
app/types/agent_state.py
app/types/common_types.py
app/types/event_types.py
app/types/hardware_types.py
app/types/request_models.py
app/types/response_models.py
app/utils/__init__.py
app/utils/logger.py
app/utils/task_manager.py
isa_cli/__init__.py
isa_agent_cli-1.0.0.dist-info/METADATA
isa_agent_cli-1.0.0.dist-info/WHEEL
isa_agent_cli-1.0.0.dist-info/entry_points.txt
isa_agent_cli-1.0.0.dist-info/top_level.txt
isa_agent_cli-1.0.0.dist-info/RECORD
